Metadata-Version: 2.4
Name: r2morph
Version: 0.1.0
Summary: A metamorphic binary transformation engine based on r2pipe and radare2
Author-email: Marc Rivero <mriverolopez@gmail.com>
Maintainer-email: Marc Rivero <mriverolopez@gmail.com>
License: MIT
Project-URL: Homepage, https://github.com/seifreed/r2morph
Project-URL: Documentation, https://github.com/seifreed/r2morph/blob/main/README.md
Project-URL: Repository, https://github.com/seifreed/r2morph
Project-URL: Issues, https://github.com/seifreed/r2morph/issues
Project-URL: Source Code, https://github.com/seifreed/r2morph
Project-URL: Bug Tracker, https://github.com/seifreed/r2morph/issues
Keywords: binary-analysis,metamorphic,code-transformation,radare2,r2pipe,reverse-engineering,binary-mutation
Classifier: Development Status :: 3 - Alpha
Classifier: Intended Audience :: Developers
Classifier: Intended Audience :: Science/Research
Classifier: License :: OSI Approved :: MIT License
Classifier: Programming Language :: Python :: 3
Classifier: Programming Language :: Python :: 3.10
Classifier: Programming Language :: Python :: 3.11
Classifier: Programming Language :: Python :: 3.12
Classifier: Programming Language :: Python :: 3.13
Classifier: Topic :: Security
Classifier: Topic :: Software Development :: Disassemblers
Classifier: Topic :: System :: Software Distribution
Requires-Python: >=3.10
License-File: LICENSE
Requires-Dist: r2pipe>=1.9.0
Requires-Dist: capstone>=5.0.0
Requires-Dist: keystone-engine>=0.9.2
Requires-Dist: pydantic>=2.0.0
Requires-Dist: rich>=13.0.0
Requires-Dist: typer>=0.9.0
Provides-Extra: dev
Requires-Dist: pytest>=7.4.0; extra == "dev"
Requires-Dist: pytest-cov>=4.1.0; extra == "dev"
Requires-Dist: pytest-mock>=3.11.1; extra == "dev"
Requires-Dist: black>=23.0.0; extra == "dev"
Requires-Dist: ruff>=0.1.0; extra == "dev"
Requires-Dist: mypy>=1.5.0; extra == "dev"
Requires-Dist: ipython>=8.12.0; extra == "dev"
Provides-Extra: docs
Requires-Dist: mkdocs>=1.5.0; extra == "docs"
Requires-Dist: mkdocs-material>=9.0.0; extra == "docs"
Requires-Dist: mkdocstrings[python]>=0.22.0; extra == "docs"
Dynamic: license-file
